pyaon.pyi
pyaon.pypy310-pp73-x86_64-linux-gnu.so
pyaon-1.1.7.dist-info/top_level.txt
pyaon-1.1.7.dist-info/LICENSE-3RD-PARTY
pyaon-1.1.7.dist-info/RECORD
pyaon-1.1.7.dist-info/WHEEL
pyaon-1.1.7.dist-info/METADATA
