Metadata-Version: 2.1
Name: pyaon
Version: 1.1.7
Summary: python bindings for the aon library
Home-page: https://github.com/Tomcat-42/pyaon
Author: Pablo Alessandro Santos Hugen
Author-email: pablohuggem@gmail.com
License: Public Domain
Keywords: text file format serialization deserialization binary data compression
Classifier: Development Status :: 4 - Beta
Classifier: Intended Audience :: Developers
Classifier: Programming Language :: Python :: 3.7
Requires-Python: >=3.5, <4
License-File: LICENSE-3RD-PARTY
